cygx1/__init__.py
cygx1/cli.py
cygx1/command/__init__.py
cygx1/command/explorer.py
cygx1/exception/__init__.py
cygx1/module/__init__.py
cygx1/module/archive.py
cygx1/module/checksum.py
cygx1/module/facts.py
cygx1/module/file_system.py
cygx1/module/logger.py
cygx1/module/nasa.py
cygx1-0.1.14.dist-info/LICENSE.txt
cygx1-0.1.14.dist-info/METADATA
cygx1-0.1.14.dist-info/WHEEL
cygx1-0.1.14.dist-info/entry_points.txt
cygx1-0.1.14.dist-info/top_level.txt
cygx1-0.1.14.dist-info/RECORD
