Metadata-Version: 2.1
Name: cygx1
Version: 0.1.14
Summary: The immensity of the universe is difficult to grasp.
Home-page: https://github.com/Clivern/CygnusX1/
Author: Clivern
Author-email: hello@clivern.com
License: MIT
Project-URL: Documentation, https://github.com/Clivern/CygnusX1/
Project-URL: Source, https://github.com/Clivern/CygnusX1/
Project-URL: Changelog, https://github.com/Clivern/CygnusX1/blob/main/CHANGELOG.rst
Project-URL: Tracker, https://github.com/Clivern/CygnusX1/issues
Project-URL: Download, https://pypi.org/project/CygnusX1/#files
Platform: any
Classifier: Development Status :: 5 - Production/Stable
Classifier: Programming Language :: Python
Classifier: License :: OSI Approved :: MIT License
License-File: LICENSE.txt
Requires-Dist: click <=8.1.7
Requires-Dist: requests <=2.32.3
Requires-Dist: importlib-metadata <=8.1.0 ; python_version < "3.8"
